node_edge/__init__.py
node_edge/_engine.py
node_edge/_utils.py
node_edge/exceptions.py
node_edge/runtime.js
node_edge-0.1.0.dist-info/LICENSE
node_edge-0.1.0.dist-info/METADATA
node_edge-0.1.0.dist-info/WHEEL
node_edge-0.1.0.dist-info/RECORD
