Metadata-Version: 2.1
Name: node-edge
Version: 0.1.0
Summary: A tool to run Node code from Python
Home-page: https://github.com/ModelW/py-node-edge
License: WTFPL
Keywords: node,javascript,binding
Author: Rémy Sanchez
Author-email: remy.sanchez@hyperthese.net
Requires-Python: >=3.10,<4.0
Classifier: License :: Other/Proprietary License
Classifier: Programming Language :: Python :: 3
Classifier: Programming Language :: Python :: 3.10
Classifier: Programming Language :: Python :: 3.11
Project-URL: Documentation, https://node-edge.rtfd.io
Project-URL: Repository, https://github.com/ModelW/py-node-edge
